{
  "districts": [
    {
      "ນະຄອນຫລວງວຽງຈັນ": [
        {
          "did": "101",
          "dn": "ຈັນທະບູລີ",
          "dn_en": "Chanthabuly",
          "pid": "1"
        },
        {
          "did": "102",
          "dn": "ສີໂຄດຕະບອງ",
          "dn_en": "Sikhottabong",
          "pid": "1"
        },
        {
          "did": "103",
          "dn": "ໄຊເສດຖາ",
          "dn_en": "Xaysetha",
          "pid": "1"
        },
        {
          "did": "104",
          "dn": "ສີສັດຕະນາກ",
          "dn_en": "Sisattanak",
          "pid": "1"
        },
        {
          "did": "105",
          "dn": "ນາຊາຍທອງ",
          "dn_en": "Naxaithong",
          "pid": "1"
        },
        {
          "did": "106",
          "dn": "ໄຊທານີ",
          "dn_en": "Xaythany",
          "pid": "1"
        },
        {
          "did": "107",
          "dn": "ຫາດຊາຍຟອງ",
          "dn_en": "Hadxaifong",
          "pid": "1"
        },
        {
          "did": "108",
          "dn": "ສັງທອງ",
          "dn_en": "Sangthong",
          "pid": "1"
        },
        {
          "did": "109",
          "dn": "ປາກງື່ມ",
          "dn_en": "Parkngum",
          "pid": "1"
        },
        {
          "did": "201",
          "dn": "ຜົ້ງສາລີ",
          "dn_en": "Phongsaly",
          "pid": "2"
        }
      ]
    },
    {
      "ຜົ້ງສາລີ": [
        {
          "did": "202",
          "dn": "ໃຫມ່",
          "dn_en": "May",
          "pid": "2"
        },
        {
          "did": "203",
          "dn": "ຂວາ",
          "dn_en": "Khua",
          "pid": "2"
        },
        {
          "did": "204",
          "dn": "ສຳພັນ",
          "dn_en": "Samphanh",
          "pid": "2"
        },
        {
          "did": "205",
          "dn": "ບູນເຫນືອ",
          "dn_en": "Bounneua",
          "pid": "2"
        },
        {
          "did": "206",
          "dn": "ຍອດອູ",
          "dn_en": "Nhot ou",
          "pid": "2"
        },
        {
          "did": "207",
          "dn": "ບູນໃຕ້",
          "dn_en": "Boontai",
          "pid": "2"
        }
      ]
    },
    {
      "ຫລວງນ້ຳທາ": [
        {
          "did": "301",
          "dn": "ຫລວງນ້ຳທາ",
          "dn_en": "Luangnamtha",
          "pid": "3"
        },
        {
          "did": "302",
          "dn": "ສິງ",
          "dn_en": "Sing",
          "pid": "3"
        },
        {
          "did": "303",
          "dn": "ລອງ",
          "dn_en": "Long",
          "pid": "3"
        },
        {
          "did": "304",
          "dn": "ວຽງພູຄາ",
          "dn_en": "Viengphoukha",
          "pid": "3"
        },
        {
          "did": "305",
          "dn": "ນາແລ",
          "dn_en": "Nalae",
          "pid": "3"
        }
      ]
    },
    {
      "ອຸດົມໄຊ": [
        {
          "did": "401",
          "dn": "ໄຊ",
          "dn_en": "Xay",
          "pid": "4"
        },
        {
          "did": "402",
          "dn": "ຫລາ",
          "dn_en": "La",
          "pid": "4"
        },
        {
          "did": "403",
          "dn": "ນາໝໍ້ ",
          "dn_en": "Namor",
          "pid": "4"
        },
        {
          "did": "404",
          "dn": "ງາ",
          "dn_en": "Nga",
          "pid": "4"
        },
        {
          "did": "405",
          "dn": "ແບງ",
          "dn_en": "Beng",
          "pid": "4"
        },
        {
          "did": "406",
          "dn": "ຮຸນ",
          "dn_en": "Hoon",
          "pid": "4"
        },
        {
          "did": "407",
          "dn": "ປາກແບງ",
          "dn_en": "Pakbeng",
          "pid": "4"
        }
      ]
    },
    {
      "ບໍ່ແກ້ວ": [
        {
          "did": "501",
          "dn": "ຫ້ວຍຊາຍ",
          "dn_en": "Houixay",
          "pid": "5"
        },
        {
          "did": "502",
          "dn": "ຕົ້ນເຜິ້ງ",
          "dn_en": "Tongpheung",
          "pid": "5"
        },
        {
          "did": "503",
          "dn": "ເມິງ",
          "dn_en": "Meung",
          "pid": "5"
        },
        {
          "did": "504",
          "dn": "ຜາອຸດົມ",
          "dn_en": "Phaoudom",
          "pid": "5"
        },
        {
          "did": "505",
          "dn": "ປາກທາ",
          "dn_en": "Paktha",
          "pid": "5"
        }
      ]
    },
    {
      "ຫຼວງພະບາງ": [
        {
          "did": "601",
          "dn": "ຫຼວງພະບາງ",
          "dn_en": "Luangprabang",
          "pid": "6"
        },
        {
          "did": "602",
          "dn": "ຊຽງເງິນ",
          "dn_en": "Xiengngeun",
          "pid": "6"
        },
        {
          "did": "603",
          "dn": "ນານ",
          "dn_en": "Nan",
          "pid": "6"
        },
        {
          "did": "604",
          "dn": "ປາກອູ",
          "dn_en": "Parkou",
          "pid": "6"
        },
        {
          "did": "605",
          "dn": "ນ້ຳບາກ",
          "dn_en": "Nambak",
          "pid": "6"
        },
        {
          "did": "606",
          "dn": "ງອຍ",
          "dn_en": "Ngoi",
          "pid": "6"
        },
        {
          "did": "607",
          "dn": "ປາກແຊງ",
          "dn_en": "Pakxeng",
          "pid": "6"
        },
        {
          "did": "608",
          "dn": "ໂພນໄຊ",
          "dn_en": "Phonxay",
          "pid": "6"
        },
        {
          "did": "609",
          "dn": "ຈອມເພັດ",
          "dn_en": "Chomphet",
          "pid": "6"
        },
        {
          "did": "610",
          "dn": "ວຽງຄຳ",
          "dn_en": "Viengkham",
          "pid": "6"
        },
        {
          "did": "611",
          "dn": "ພູຄູນ",
          "dn_en": "Phoukhoune",
          "pid": "6"
        },
        {
          "did": "612",
          "dn": "ໂພນທອງ",
          "dn_en": "Phonthong",
          "pid": "6"
        }
      ]
    },
    {
      "ຫົວພັນ": [
        {
          "did": "701",
          "dn": "ຊຳເໜືອ",
          "dn_en": "Xamneua",
          "pid": "7"
        },
        {
          "did": "702",
          "dn": "ຊຽງຄໍ້",
          "dn_en": "Xiengkhor",
          "pid": "7"
        },
        {
          "did": "703",
          "dn": "ຮ້ຽມ",
          "dn_en": "Hiam",
          "pid": "7"
        },
        {
          "did": "704",
          "dn": "ວຽງໄຊ",
          "dn_en": "Viengxay",
          "pid": "7"
        },
        {
          "did": "705",
          "dn": "ຫົວເມືອງ",
          "dn_en": "Huameuang",
          "pid": "7"
        },
        {
          "did": "706",
          "dn": "ຊຳໃຕ້",
          "dn_en": "Xamtay",
          "pid": "7"
        },
        {
          "did": "707",
          "dn": "ສົບເບົາ",
          "dn_en": "Sopbao",
          "pid": "7"
        },
        {
          "did": "708",
          "dn": "ແອດ",
          "dn_en": "Add",
          "pid": "7"
        },
        {
          "did": "709",
          "dn": "ກວັນ",
          "dn_en": "Kuan",
          "pid": "7"
        },
        {
          "did": "710",
          "dn": "ຊອນ",
          "dn_en": "Xone",
          "pid": "7"
        }
      ]
    },
    {
      "ໄຊຍະບູລີ": [
        {
          "did": "801",
          "dn": "ໄຊຍະບູລີ",
          "dn_en": "Xayabury",
          "pid": "8"
        },
        {
          "did": "802",
          "dn": "ຄອບ",
          "dn_en": "Khop",
          "pid": "8"
        },
        {
          "did": "803",
          "dn": "ຫົງສາ",
          "dn_en": "Hongsa",
          "pid": "8"
        },
        {
          "did": "804",
          "dn": "ເງິນ",
          "dn_en": "Ngeun",
          "pid": "8"
        },
        {
          "did": "805",
          "dn": "ຊຽງຮ່ອນ",
          "dn_en": "Xienghone",
          "pid": "8"
        },
        {
          "did": "806",
          "dn": "ພຽງ",
          "dn_en": "Phieng",
          "pid": "8"
        },
        {
          "did": "807",
          "dn": "ປາກລາຍ",
          "dn_en": "Parklai",
          "pid": "8"
        },
        {
          "did": "808",
          "dn": "ແກ່ນທ້າວ",
          "dn_en": "Kenethao",
          "pid": "8"
        },
        {
          "did": "809",
          "dn": "ບໍ່ແຕນ",
          "dn_en": "Botene",
          "pid": "8"
        },
        {
          "did": "810",
          "dn": "ທົ່ງມີໄຊ",
          "dn_en": "Thongmyxay",
          "pid": "8"
        },
        {
          "did": "811",
          "dn": "ໄຊຊະຖານ",
          "dn_en": "Xaysathan",
          "pid": "8"
        }
      ]
    },
    {
      "ຊຽງຂວາງ": [
        {
          "did": "901",
          "dn": "ແປກ",
          "dn_en": "Pek",
          "pid": "9"
        },
        {
          "did": "902",
          "dn": "ຄຳ",
          "dn_en": "Kham",
          "pid": "9"
        },
        {
          "did": "903",
          "dn": "ໜອງແຮດ",
          "dn_en": "Nonghed",
          "pid": "9"
        },
        {
          "did": "904",
          "dn": "ຄູນ",
          "dn_en": "Khoune",
          "pid": "9"
        },
        {
          "did": "905",
          "dn": "ໝອກ",
          "dn_en": "Mork",
          "pid": "9"
        },
        {
          "did": "906",
          "dn": "ພູກູດ",
          "dn_en": "Phookood",
          "pid": "9"
        },
        {
          "did": "907",
          "dn": "ຜາໄຊ",
          "dn_en": "Phaxay",
          "pid": "9"
        }
      ]
    },
    {
      "ວຽງຈັນ": [
        {
          "did": "1001",
          "dn": "ໂພນໂຮງ",
          "dn_en": "Phonhong",
          "pid": "10"
        },
        {
          "did": "1002",
          "dn": "ທຸລະຄົມ",
          "dn_en": "Thoulakhom",
          "pid": "10"
        },
        {
          "did": "1003",
          "dn": "ແກ້ວອຸດົມ",
          "dn_en": "Keooudom",
          "pid": "10"
        },
        {
          "did": "1004",
          "dn": "ກາສີ",
          "dn_en": "Kasy",
          "pid": "10"
        },
        {
          "did": "1005",
          "dn": "ວັງວຽງ",
          "dn_en": "Vangvieng",
          "pid": "10"
        },
        {
          "did": "1006",
          "dn": "ເຟືອງ",
          "dn_en": "Feuang",
          "pid": "10"
        },
        {
          "did": "1007",
          "dn": "ຊະນະຄາມ",
          "dn_en": "Xanakham",
          "pid": "10"
        },
        {
          "did": "1008",
          "dn": "ແມດ",
          "dn_en": "Mad",
          "pid": "10"
        },
        {
          "did": "1009",
          "dn": "ວຽງຄຳ",
          "dn_en": "Viengkham",
          "pid": "10"
        },
        {
          "did": "1010",
          "dn": "ຫີນເຫີບ",
          "dn_en": "Hinherb",
          "pid": "10"
        },
        {
          "did": "1012",
          "dn": "ໝື່ນ",
          "dn_en": "Meun",
          "pid": "10"
        }
      ]
    },
    {
      "ບໍລິຄຳໄຊ": [
        {
          "did": "1101",
          "dn": "ປາກຊັນ",
          "dn_en": "Pakxane",
          "pid": "11"
        },
        {
          "did": "1102",
          "dn": "ທ່າພະບາດ",
          "dn_en": "Thaphabath",
          "pid": "11"
        },
        {
          "did": "1103",
          "dn": "ປາກກະດິງ",
          "dn_en": "Pakkading",
          "pid": "11"
        },
        {
          "did": "1104",
          "dn": "ບໍລິຄັນ",
          "dn_en": "Bolikhanh",
          "pid": "11"
        },
        {
          "did": "1105",
          "dn": "ຄຳເກີດ",
          "dn_en": "Khamkheuth",
          "pid": "11"
        },
        {
          "did": "1106",
          "dn": "ວຽງທອງ",
          "dn_en": "Viengthong",
          "pid": "11"
        },
        {
          "did": "1107",
          "dn": "ໄຊຈຳພອນ",
          "dn_en": "Xaychamphone",
          "pid": "11"
        }
      ]
    },
    {
      "ຄຳມ່ວນ": [
        {
          "did": "1201",
          "dn": "ທ່າແຂກ",
          "dn_en": "Thakhek",
          "pid": "12"
        },
        {
          "did": "1202",
          "dn": "ມະຫາໄຊ",
          "dn_en": "Mahaxay",
          "pid": "12"
        },
        {
          "did": "1203",
          "dn": "ໜອງບົກ",
          "dn_en": "Nongbok",
          "pid": "12"
        },
        {
          "did": "1204",
          "dn": "ຫີນບູນ",
          "dn_en": "Hinboon",
          "pid": "12"
        },
        {
          "did": "1205",
          "dn": "ຍົມມະລາດ",
          "dn_en": "Nhommalath",
          "pid": "12"
        },
        {
          "did": "1206",
          "dn": "ບົວລະພາ",
          "dn_en": "Bualapha",
          "pid": "12"
        },
        {
          "did": "1207",
          "dn": "ນາກາຍ",
          "dn_en": "Nakai",
          "pid": "12"
        },
        {
          "did": "1208",
          "dn": "ເຊບັ້ງໄຟ",
          "dn_en": "Xebangfay",
          "pid": "12"
        },
        {
          "did": "1209",
          "dn": "ໄຊບົວທອງ",
          "dn_en": "Xaybuathong",
          "pid": "12"
        },
        {
          "did": "1210",
          "dn": "ຄູນຄຳ",
          "dn_en": "Khounkham",
          "pid": "12"
        }
      ]
    },
    {
      "ສະຫວັນນະເຂດ": [
        {
          "did": "1301",
          "dn": "ໄກສອນ ພົມວິຫານ",
          "dn_en": "Kaisone Phomvihane",
          "pid": "13"
        },
        {
          "did": "1302",
          "dn": "ອຸທຸມພອນ",
          "dn_en": "Outhoumphone",
          "pid": "13"
        },
        {
          "did": "1303",
          "dn": "ອາດສະພັງທອງ",
          "dn_en": "Atsaphangthong",
          "pid": "13"
        },
        {
          "did": "1304",
          "dn": "ພີນ",
          "dn_en": "Phine",
          "pid": "13"
        },
        {
          "did": "1305",
          "dn": "ເຊໂປນ",
          "dn_en": "Xepon",
          "pid": "13"
        },
        {
          "did": "1306",
          "dn": "ນອງ",
          "dn_en": "Nong",
          "pid": "13"
        },
        {
          "did": "1307",
          "dn": "ທ່າປາງທອງ",
          "dn_en": "Thapangthong",
          "pid": "13"
        },
        {
          "did": "1308",
          "dn": "ສອງຄອນ",
          "dn_en": "Songkhone",
          "pid": "13"
        },
        {
          "did": "1309",
          "dn": "ຈຳພອນ",
          "dn_en": "Champhone",
          "pid": "13"
        },
        {
          "did": "1310",
          "dn": "ຊົນບູລີ",
          "dn_en": "Xonbuly",
          "pid": "13"
        },
        {
          "did": "1311",
          "dn": "ໄຊບູລີ",
          "dn_en": "Xaybouly",
          "pid": "13"
        },
        {
          "did": "1312",
          "dn": "ວິລະບູລີ",
          "dn_en": "Vilabuly",
          "pid": "13"
        },
        {
          "did": "1313",
          "dn": "ອາດສະພອນ",
          "dn_en": "Atsaphone",
          "pid": "13"
        },
        {
          "did": "1314",
          "dn": "ໄຊພູທອງ",
          "dn_en": "Xayphoothong",
          "pid": "13"
        },
        {
          "did": "1315",
          "dn": "ພະລານໄຊ",
          "dn_en": "Phalanxay",
          "pid": "13"
        }
      ]
    },
    {
      "ສາລະວັນ": [
        {
          "did": "1401",
          "dn": "ສາລະວັນ",
          "dn_en": "Saravane",
          "pid": "14"
        },
        {
          "did": "1402",
          "dn": "ຕາໂອ້ຍ",
          "dn_en": "Ta oi",
          "pid": "14"
        },
        {
          "did": "1403",
          "dn": "ຕຸ້ມລານ",
          "dn_en": "Toomlam",
          "pid": "14"
        },
        {
          "did": "1404",
          "dn": "ລະຄອນເພັງ",
          "dn_en": "Lakhonepheng",
          "pid": "14"
        },
        {
          "did": "1405",
          "dn": "ວາປີ",
          "dn_en": "Vapy",
          "pid": "14"
        },
        {
          "did": "1406",
          "dn": "ຄົງເຊໂດນ",
          "dn_en": "Kongxedone",
          "pid": "14"
        },
        {
          "did": "1407",
          "dn": "ເລົ່າງາມ",
          "dn_en": "Lao ngarm",
          "pid": "14"
        },
        {
          "did": "1408",
          "dn": "ສະມ້ວຍ",
          "dn_en": "Samoi",
          "pid": "14"
        }
      ]
    },
    {
      "ເຊກອງ": [
        {
          "did": "1501",
          "dn": "ລະມາມ",
          "dn_en": "Lamarm",
          "pid": "15"
        },
        {
          "did": "1502",
          "dn": "ກະລືມ",
          "dn_en": "Kaleum",
          "pid": "15"
        },
        {
          "did": "1503",
          "dn": "ດາກຈຶງ",
          "dn_en": "Dakcheung",
          "pid": "15"
        },
        {
          "did": "1504",
          "dn": "ທ່າແຕງ",
          "dn_en": "Thateng",
          "pid": "15"
        }
      ]
    },
    {
      "ຈຳປາສັກ": [
        {
          "did": "1601",
          "dn": "ປາກເຊ",
          "dn_en": "Pakse",
          "pid": "16"
        },
        {
          "did": "1602",
          "dn": "ຊະນະສົມບູນ",
          "dn_en": "Sanasomboon",
          "pid": "16"
        },
        {
          "did": "1603",
          "dn": "ບາຈຽງຈະເລີນສຸກ",
          "dn_en": "Bachiangchaleunsook",
          "pid": "16"
        },
        {
          "did": "1604",
          "dn": "ປາກຊ່ອງ",
          "dn_en": "Pakxong",
          "pid": "16"
        },
        {
          "did": "1605",
          "dn": "ປະທຸມພອນ",
          "dn_en": "Pathoumphone",
          "pid": "16"
        },
        {
          "did": "1606",
          "dn": "ໂພນທອງ",
          "dn_en": "Phonthong",
          "pid": "16"
        },
        {
          "did": "1607",
          "dn": "ຈຳປາສັກ",
          "dn_en": "Champasak",
          "pid": "16"
        },
        {
          "did": "1608",
          "dn": "ສຸຂຸມາ",
          "dn_en": "Sukhuma",
          "pid": "16"
        },
        {
          "did": "1609",
          "dn": "ມຸນລະປະໂມກ",
          "dn_en": "Moonlapamok",
          "pid": "16"
        },
        {
          "did": "1610",
          "dn": "ໂຂງ",
          "dn_en": "Khong",
          "pid": "16"
        }
      ]
    },
    {
      "ອັດຕະປື": [
        {
          "did": "1701",
          "dn": "ໄຊເສດຖາ",
          "dn_en": "Xaysettha",
          "pid": "17"
        },
        {
          "did": "1702",
          "dn": "ສາມະຄີໄຊ",
          "dn_en": "Samakkixay",
          "pid": "17"
        },
        {
          "did": "1703",
          "dn": "ສະໜາມໄຊ",
          "dn_en": "Sanamxay",
          "pid": "17"
        },
        {
          "did": "1704",
          "dn": "ສານໄຊ",
          "dn_en": "Sanxay",
          "pid": "17"
        },
        {
          "did": "1705",
          "dn": "ພູວົງ",
          "dn_en": "Phouvong",
          "pid": "17"
        }
      ]
    },
    {
      "ໄຊສົມບູນ": [
        {
          "did": "1801",
          "dn": "ອານຸວົງ",
          "dn_en": "Anouvong",
          "pid": "18"
        },
        {
          "did": "1802",
          "dn": "ທ່າໂທມ",
          "dn_en": "Thathom",
          "pid": "18"
        },
        {
          "did": "1803",
          "dn": "ລ້ອງແຈ້ງ",
          "dn_en": "Longcheng",
          "pid": "18"
        },
        {
          "did": "1804",
          "dn": "ຮົ່ມ",
          "dn_en": "Hom",
          "pid": "18"
        },
        {
          "did": "1805",
          "dn": "ລ້ອງຊານ",
          "dn_en": "Longsan",
          "pid": "18"
        }
      ]
    }
  ]
}
